eth_ipc_client/__init__.py
eth_ipc_client/client.py
eth_ipc_client/utils.py
ethereum_ipc_client-0.1.9.dist-info/DESCRIPTION.rst
ethereum_ipc_client-0.1.9.dist-info/METADATA
ethereum_ipc_client-0.1.9.dist-info/metadata.json
ethereum_ipc_client-0.1.9.dist-info/RECORD
ethereum_ipc_client-0.1.9.dist-info/top_level.txt
ethereum_ipc_client-0.1.9.dist-info/WHEEL
